fair_loss.py
fair_loss-0.5.dist-info/LICENSE.txt
fair_loss-0.5.dist-info/METADATA
fair_loss-0.5.dist-info/WHEEL
fair_loss-0.5.dist-info/top_level.txt
fair_loss-0.5.dist-info/RECORD
