Metadata-Version: 2.1
Name: fair-loss
Version: 0.5
Summary: A fair loss function
Home-page: https://pypi.org/project/fair-loss/
Author: Vincent Lequertier
Author-email: vi.le@autistici.org
License: UNKNOWN
Project-URL: Bug Reports, https://gitlab.com/vi.le/fair-loss/-/issues
Project-URL: Documentation, http://vi.le.gitlab.io/fair-loss/
Project-URL: Source, https://gitlab.com/vi.le/fair-loss
Keywords: pytorch loss fair
Platform: UNKNOWN
Classifier: Development Status :: 3 - Alpha
Classifier: Intended Audience :: Developers
Classifier: Topic :: Scientific/Engineering :: Artificial Intelligence
Classifier: License :: OSI Approved :: GNU General Public License v3 (GPLv3)
Classifier: Programming Language :: Python :: 3
Classifier: Programming Language :: Python :: 3.5
Classifier: Programming Language :: Python :: 3.6
Classifier: Programming Language :: Python :: 3.7
Classifier: Programming Language :: Python :: 3.8
Requires-Python: >=3.5, <4
Requires-Dist: torch
